LICENSE
README.md
setup.cfg
setup.py
RupineLib/__init__.py
RupineLib/dataLoadJobHelper.py
RupineLib/db.py
RupineLib/defichain.py
RupineLib/taskSetup.py
RupineLib/timer.py
RupineLib/utils.py
RupineLib.egg-info/PKG-INFO
RupineLib.egg-info/SOURCES.txt
RupineLib.egg-info/dependency_links.txt
RupineLib.egg-info/requires.txt
RupineLib.egg-info/top_level.txt
RupineLib/dbCode/__init__.py
RupineLib/dbCode/advancedDBOperation.py
RupineLib/dbCode/connection.py
RupineLib/dbCode/directDBOperation.py
RupineLib/defichainUtils/CustomTx.py
RupineLib/defichainUtils/__init__.py
RupineLib/defichainUtils/base58.py
RupineLib/defichainUtils/bech32.py
RupineLib/defichainUtils/customTxDecode.py
RupineLib/defichainUtils/utils.py