Metadata-Version: 2.1
Name: RupineLib
Version: 0.3.6
Summary: RupineLib
Author: RupineLabs
Author-email: <abc@def.com>
Keywords: web3
Classifier: Development Status :: 1 - Planning
Classifier: Intended Audience :: Developers
Classifier: Programming Language :: Python :: 3
Classifier: Operating System :: Unix
Classifier: Operating System :: MacOS :: MacOS X
Classifier: Operating System :: Microsoft :: Windows
License-File: LICENSE
Requires-Dist: psycopg2
Requires-Dist: pgcopy
